{
  "id": "10000100",
  "name": "Kachina",
  "rarity": 4,
  "element": "Rock",
  "weapon_type": "WEAPON_POLE",
  "icon": "https://gi.yatta.moe/assets/UI/UI_AvatarIcon_Kachina.png",
  "activeTalents": [
    {
      "name": "Cragbiter",
      "description": "Normal Attack\nPerforms up to 4 consecutive spear strikes.\n\nCharged Attack\nConsumes a certain amount of Stamina to lunge forward, dealing damage to opponents along the way.\n\nPlunging Attack\nPlunges from mid-air to strike the ground below, damaging opponents along the path and dealing AoE DMG upon impact.",
      "icon": "https://gi.yatta.moe/assets/UI/Skill_A_03.png",
      "levelCosts": [
        {
          "level": 1,
          "moraCost": null,
          "items": []
        },
        {
          "level": 2,
          "moraCost": 12500,
          "items": [
            {
              "id": 104353,
              "name": "Teachings of Conflict",
              "icon": "https://gi.yatta.moe/assets/UI/UI_ItemIcon_104353.png",
              "rarity": 2,
              "qty": 3
            },
            {
              "id": 112104,
              "name": "Sentry's Wooden Whistle",
              "icon": "https://gi.yatta.moe/assets/UI/UI_ItemIcon_112104.png",
              "rarity": 1,
              "qty": 6
            }
          ]
        },
        {
          "level": 3,
          "moraCost": 17500,
          "items": [
            {
              "id": 104354,
              "name": "Guide to Conflict",
              "icon": "https://gi.yatta.moe/assets/UI/UI_ItemIcon_104354.png",
              "rarity": 3,
              "qty": 2
            },
            {
              "id": 112105,
              "name": "Warrior's Metal Whistle",
              "icon": "https://gi.yatta.moe/assets/UI/UI_ItemIcon_112105.png",
              "rarity": 2,
              "qty": 3
            }
          ]
        },
        {
          "level": 4,
          "moraCost": 25000,
          "items": [
            {
              "id": 104354,
              "name": "Guide to Conflict",
              "icon": "https://gi.yatta.moe/assets/UI/UI_ItemIcon_104354.png",
              "rarity": 3,
              "qty": 4
            },
            {
              "id": 112105,
              "name": "Warrior's Metal Whistle",
              "icon": "https://gi.yatta.moe/assets/UI/UI_ItemIcon_112105.png",
              "rarity": 2,
              "qty": 4
            }
          ]
        },
        {
          "level": 5,
          "moraCost": 30000,
          "items": [
            {
              "id": 104354,
              "name": "Guide to Conflict",
              "icon": "https://gi.yatta.moe/assets/UI/UI_ItemIcon_104354.png",
              "rarity": 3,
              "qty": 6
            },
            {
              "id": 112105,
              "name": "Warrior's Metal Whistle",
              "icon": "https://gi.yatta.moe/assets/UI/UI_ItemIcon_112105.png",
              "rarity": 2,
              "qty": 6
            }
          ]
        },
        {
          "level": 6,
          "moraCost": 37500,
          "items": [
            {
              "id": 104354,
              "name": "Guide to Conflict",
              "icon": "https://gi.yatta.moe/assets/UI/UI_ItemIcon_104354.png",
              "rarity": 3,
              "qty": 9
            },
            {
              "id": 112105,
              "name": "Warrior's Metal Whistle",
              "icon": "https://gi.yatta.moe/assets/UI/UI_ItemIcon_112105.png",
              "rarity": 2,
              "qty": 9
            }
          ]
        },
        {
          "level": 7,
          "moraCost": 120000,
          "items": [
            {
              "id": 104355,
              "name": "Philosophies of Conflict",
              "icon": "https://gi.yatta.moe/assets/UI/UI_ItemIcon_104355.png",
              "rarity": 4,
              "qty": 4
            },
            {
              "id": 112106,
              "name": "Saurian-Crowned Warrior's Golden Whistle",
              "icon": "https://gi.yatta.moe/assets/UI/UI_ItemIcon_112106.png",
              "rarity": 3,
              "qty": 4
            },
            {
              "id": 113060,
              "name": "Fading Candle",
              "icon": "https://gi.yatta.moe/assets/UI/UI_ItemIcon_113060.png",
              "rarity": 5,
              "qty": 1
            }
          ]
        },
        {
          "level": 8,
          "moraCost": 260000,
          "items": [
            {
              "id": 104355,
              "name": "Philosophies of Conflict",
              "icon": "https://gi.yatta.moe/assets/UI/UI_ItemIcon_104355.png",
              "rarity": 4,
              "qty": 6
            },
            {
              "id": 112106,
              "name": "Saurian-Crowned Warrior's Golden Whistle",
              "icon": "https://gi.yatta.moe/assets/UI/UI_ItemIcon_112106.png",
              "rarity": 3,
              "qty": 6
            },
            {
              "id": 113060,
              "name": "Fading Candle",
              "icon": "https://gi.yatta.moe/assets/UI/UI_ItemIcon_113060.png",
              "rarity": 5,
              "qty": 1
            }
          ]
        },
        {
          "level": 9,
          "moraCost": 450000,
          "items": [
            {
              "id": 104355,
              "name": "Philosophies of Conflict",
              "icon": "https://gi.yatta.moe/assets/UI/UI_ItemIcon_104355.png",
              "rarity": 4,
              "qty": 12
            },
            {
              "id": 112106,
              "name": "Saurian-Crowned Warrior's Golden Whistle",
              "icon": "https://gi.yatta.moe/assets/UI/UI_ItemIcon_112106.png",
              "rarity": 3,
              "qty": 9
            },
            {
              "id": 113060,
              "name": "Fading Candle",
              "icon": "https://gi.yatta.moe/assets/UI/UI_ItemIcon_113060.png",
              "rarity": 5,
              "qty": 2
            }
          ]
        },
        {
          "level": 10,
          "moraCost": 700000,
          "items": [
            {
              "id": 104319,
              "name": "Crown of Insight",
              "icon": "https://gi.yatta.moe/assets/UI/UI_ItemIcon_104319.png",
              "rarity": 5,
              "qty": 1
            },
            {
              "id": 104355,
              "name": "Philosophies of Conflict",
              "icon": "https://gi.yatta.moe/assets/UI/UI_ItemIcon_104355.png",
              "rarity": 4,
              "qty": 16
            },
            {
              "id": 112106,
              "name": "Saurian-Crowned Warrior's Golden Whistle",
              "icon": "https://gi.yatta.moe/assets/UI/UI_ItemIcon_112106.png",
              "rarity": 3,
              "qty": 12
            },
            {
              "id": 113060,
              "name": "Fading Candle",
              "icon": "https://gi.yatta.moe/assets/UI/UI_ItemIcon_113060.png",
              "rarity": 5,
              "qty": 2
            }
          ]
        },
        {
          "level": 11,
          "moraCost": null,
          "items": []
        },
        {
          "level": 12,
          "moraCost": null,
          "items": []
        },
        {
          "level": 13,
          "moraCost": null,
          "items": []
        },
        {
          "level": 14,
          "moraCost": null,
          "items": []
        },
        {
          "level": 15,
          "moraCost": null,
          "items": []
        }
      ]
    },
    {
      "name": "Go, Go Turbo Twirly!",
      "description": "Fight alongside the turbo trusty Turbo Twirly!\nSummons Turbo Twirly. When the skill is Held and released, Kachina will summon and ride Turbo Twirly.\nAfter the Skill is used, Kachina will gain 60 Nightsoul points and enter the Nightsoul's Blessing state.\n\nNightsoul's Blessing: Kachina\nTurbo Twirly's various actions consume Kachina's Nightsoul points.\nThe Nightsoul's Blessing state will end when these points have been depleted.\n\nTurbo Twirly\nCan exist independently or be ridden and operated by Kachina. When Turbo Twirly is present, Kachina's Elemental Skill, \"Go, Go Turbo Twirly!\", will change to an option to Mount/Dismount Turbo Twirly.\n·When present independent of Kachina, it will slam the ground at intervals, dealing Nightsoul-aligned AoE Geo DMG based on Kachina's DEF.\n·When Kachina is riding Turbo Twirly, she can control it to move and climb swiftly, and use Normal Attacks to slam the ground, dealing Nightsoul-aligned AoE Geo DMG based on Kachina's DEF.\n\nTurbo Twirly will disappear once Kachina's Nightsoul's Blessing state ends, and it is considered a Geo Construct. Only 1 Turbo Twirly created by Kachina herself can exist on the field at any one time.\n\nTurbo Twirly only looks like a top — it is, in fact, a drill that can split even the strongest rock asunder!",
      "icon": "https://gi.yatta.moe/assets/UI/Skill_S_Kachina_01.png",
      "levelCosts": [
        {
          "level": 1,
          "moraCost": null,
          "items": []
        },
        {
          "level": 2,
          "moraCost": 12500,
          "items": [
            {
              "id": 104353,
              "name": "Teachings of Conflict",
              "icon": "https://gi.yatta.moe/assets/UI/UI_ItemIcon_104353.png",
              "rarity": 2,
              "qty": 3
            },
            {
              "id": 112104,
              "name": "Sentry's Wooden Whistle",
              "icon": "https://gi.yatta.moe/assets/UI/UI_ItemIcon_112104.png",
              "rarity": 1,
              "qty": 6
            }
          ]
        },
        {
          "level": 3,
          "moraCost": 17500,
          "items": [
            {
              "id": 104354,
              "name": "Guide to Conflict",
              "icon": "https://gi.yatta.moe/assets/UI/UI_ItemIcon_104354.png",
              "rarity": 3,
              "qty": 2
            },
            {
              "id": 112105,
              "name": "Warrior's Metal Whistle",
              "icon": "https://gi.yatta.moe/assets/UI/UI_ItemIcon_112105.png",
              "rarity": 2,
              "qty": 3
            }
          ]
        },
        {
          "level": 4,
          "moraCost": 25000,
          "items": [
            {
              "id": 104354,
              "name": "Guide to Conflict",
              "icon": "https://gi.yatta.moe/assets/UI/UI_ItemIcon_104354.png",
              "rarity": 3,
              "qty": 4
            },
            {
              "id": 112105,
              "name": "Warrior's Metal Whistle",
              "icon": "https://gi.yatta.moe/assets/UI/UI_ItemIcon_112105.png",
              "rarity": 2,
              "qty": 4
            }
          ]
        },
        {
          "level": 5,
          "moraCost": 30000,
          "items": [
            {
              "id": 104354,
              "name": "Guide to Conflict",
              "icon": "https://gi.yatta.moe/assets/UI/UI_ItemIcon_104354.png",
              "rarity": 3,
              "qty": 6
            },
            {
              "id": 112105,
              "name": "Warrior's Metal Whistle",
              "icon": "https://gi.yatta.moe/assets/UI/UI_ItemIcon_112105.png",
              "rarity": 2,
              "qty": 6
            }
          ]
        },
        {
          "level": 6,
          "moraCost": 37500,
          "items": [
            {
              "id": 104354,
              "name": "Guide to Conflict",
              "icon": "https://gi.yatta.moe/assets/UI/UI_ItemIcon_104354.png",
              "rarity": 3,
              "qty": 9
            },
            {
              "id": 112105,
              "name": "Warrior's Metal Whistle",
              "icon": "https://gi.yatta.moe/assets/UI/UI_ItemIcon_112105.png",
              "rarity": 2,
              "qty": 9
            }
          ]
        },
        {
          "level": 7,
          "moraCost": 120000,
          "items": [
            {
              "id": 104355,
              "name": "Philosophies of Conflict",
              "icon": "https://gi.yatta.moe/assets/UI/UI_ItemIcon_104355.png",
              "rarity": 4,
              "qty": 4
            },
            {
              "id": 112106,
              "name": "Saurian-Crowned Warrior's Golden Whistle",
              "icon": "https://gi.yatta.moe/assets/UI/UI_ItemIcon_112106.png",
              "rarity": 3,
              "qty": 4
            },
            {
              "id": 113060,
              "name": "Fading Candle",
              "icon": "https://gi.yatta.moe/assets/UI/UI_ItemIcon_113060.png",
              "rarity": 5,
              "qty": 1
            }
          ]
        },
        {
          "level": 8,
          "moraCost": 260000,
          "items": [
            {
              "id": 104355,
              "name": "Philosophies of Conflict",
              "icon": "https://gi.yatta.moe/assets/UI/UI_ItemIcon_104355.png",
              "rarity": 4,
              "qty": 6
            },
            {
              "id": 112106,
              "name": "Saurian-Crowned Warrior's Golden Whistle",
              "icon": "https://gi.yatta.moe/assets/UI/UI_ItemIcon_112106.png",
              "rarity": 3,
              "qty": 6
            },
            {
              "id": 113060,
              "name": "Fading Candle",
              "icon": "https://gi.yatta.moe/assets/UI/UI_ItemIcon_113060.png",
              "rarity": 5,
              "qty": 1
            }
          ]
        },
        {
          "level": 9,
          "moraCost": 450000,
          "items": [
            {
              "id": 104355,
              "name": "Philosophies of Conflict",
              "icon": "https://gi.yatta.moe/assets/UI/UI_ItemIcon_104355.png",
              "rarity": 4,
              "qty": 12
            },
            {
              "id": 112106,
              "name": "Saurian-Crowned Warrior's Golden Whistle",
              "icon": "https://gi.yatta.moe/assets/UI/UI_ItemIcon_112106.png",
              "rarity": 3,
              "qty": 9
            },
            {
              "id": 113060,
              "name": "Fading Candle",
              "icon": "https://gi.yatta.moe/assets/UI/UI_ItemIcon_113060.png",
              "rarity": 5,
              "qty": 2
            }
          ]
        },
        {
          "level": 10,
          "moraCost": 700000,
          "items": [
            {
              "id": 104319,
              "name": "Crown of Insight",
              "icon": "https://gi.yatta.moe/assets/UI/UI_ItemIcon_104319.png",
              "rarity": 5,
              "qty": 1
            },
            {
              "id": 104355,
              "name": "Philosophies of Conflict",
              "icon": "https://gi.yatta.moe/assets/UI/UI_ItemIcon_104355.png",
              "rarity": 4,
              "qty": 16
            },
            {
              "id": 112106,
              "name": "Saurian-Crowned Warrior's Golden Whistle",
              "icon": "https://gi.yatta.moe/assets/UI/UI_ItemIcon_112106.png",
              "rarity": 3,
              "qty": 12
            },
            {
              "id": 113060,
              "name": "Fading Candle",
              "icon": "https://gi.yatta.moe/assets/UI/UI_ItemIcon_113060.png",
              "rarity": 5,
              "qty": 2
            }
          ]
        },
        {
          "level": 11,
          "moraCost": null,
          "items": []
        },
        {
          "level": 12,
          "moraCost": null,
          "items": []
        },
        {
          "level": 13,
          "moraCost": null,
          "items": []
        },
        {
          "level": 14,
          "moraCost": null,
          "items": []
        },
        {
          "level": 15,
          "moraCost": null,
          "items": []
        }
      ]
    },
    {
      "name": "Time to Get Serious!",
      "description": "Striking the ground, Kachina deals AoE Geo DMG based on her DEF and creates a Turbo Drill Field.\nThe Field increases Turbo Twirly's attack AoE and its Movement SPD when Kachina is riding it.\n\nIf Kachina's own Turbo Twirly is present when this is used, the Turbo Twirly will be summoned to her side.\n\nJust as nervous performers might imagine audience members as wooden puppets, Kachina imagines that her opponents are the loveliest of gem-bearing ores — the kind you'd be proud to bring home and hoard.",
      "icon": "https://gi.yatta.moe/assets/UI/Skill_E_Kachina_01.png",
      "levelCosts": [
        {
          "level": 1,
          "moraCost": null,
          "items": []
        },
        {
          "level": 2,
          "moraCost": 12500,
          "items": [
            {
              "id": 104353,
              "name": "Teachings of Conflict",
              "icon": "https://gi.yatta.moe/assets/UI/UI_ItemIcon_104353.png",
              "rarity": 2,
              "qty": 3
            },
            {
              "id": 112104,
              "name": "Sentry's Wooden Whistle",
              "icon": "https://gi.yatta.moe/assets/UI/UI_ItemIcon_112104.png",
              "rarity": 1,
              "qty": 6
            }
          ]
        },
        {
          "level": 3,
          "moraCost": 17500,
          "items": [
            {
              "id": 104354,
              "name": "Guide to Conflict",
              "icon": "https://gi.yatta.moe/assets/UI/UI_ItemIcon_104354.png",
              "rarity": 3,
              "qty": 2
            },
            {
              "id": 112105,
              "name": "Warrior's Metal Whistle",
              "icon": "https://gi.yatta.moe/assets/UI/UI_ItemIcon_112105.png",
              "rarity": 2,
              "qty": 3
            }
          ]
        },
        {
          "level": 4,
          "moraCost": 25000,
          "items": [
            {
              "id": 104354,
              "name": "Guide to Conflict",
              "icon": "https://gi.yatta.moe/assets/UI/UI_ItemIcon_104354.png",
              "rarity": 3,
              "qty": 4
            },
            {
              "id": 112105,
              "name": "Warrior's Metal Whistle",
              "icon": "https://gi.yatta.moe/assets/UI/UI_ItemIcon_112105.png",
              "rarity": 2,
              "qty": 4
            }
          ]
        },
        {
          "level": 5,
          "moraCost": 30000,
          "items": [
            {
              "id": 104354,
              "name": "Guide to Conflict",
              "icon": "https://gi.yatta.moe/assets/UI/UI_ItemIcon_104354.png",
              "rarity": 3,
              "qty": 6
            },
            {
              "id": 112105,
              "name": "Warrior's Metal Whistle",
              "icon": "https://gi.yatta.moe/assets/UI/UI_ItemIcon_112105.png",
              "rarity": 2,
              "qty": 6
            }
          ]
        },
        {
          "level": 6,
          "moraCost": 37500,
          "items": [
            {
              "id": 104354,
              "name": "Guide to Conflict",
              "icon": "https://gi.yatta.moe/assets/UI/UI_ItemIcon_104354.png",
              "rarity": 3,
              "qty": 9
            },
            {
              "id": 112105,
              "name": "Warrior's Metal Whistle",
              "icon": "https://gi.yatta.moe/assets/UI/UI_ItemIcon_112105.png",
              "rarity": 2,
              "qty": 9
            }
          ]
        },
        {
          "level": 7,
          "moraCost": 120000,
          "items": [
            {
              "id": 104355,
              "name": "Philosophies of Conflict",
              "icon": "https://gi.yatta.moe/assets/UI/UI_ItemIcon_104355.png",
              "rarity": 4,
              "qty": 4
            },
            {
              "id": 112106,
              "name": "Saurian-Crowned Warrior's Golden Whistle",
              "icon": "https://gi.yatta.moe/assets/UI/UI_ItemIcon_112106.png",
              "rarity": 3,
              "qty": 4
            },
            {
              "id": 113060,
              "name": "Fading Candle",
              "icon": "https://gi.yatta.moe/assets/UI/UI_ItemIcon_113060.png",
              "rarity": 5,
              "qty": 1
            }
          ]
        },
        {
          "level": 8,
          "moraCost": 260000,
          "items": [
            {
              "id": 104355,
              "name": "Philosophies of Conflict",
              "icon": "https://gi.yatta.moe/assets/UI/UI_ItemIcon_104355.png",
              "rarity": 4,
              "qty": 6
            },
            {
              "id": 112106,
              "name": "Saurian-Crowned Warrior's Golden Whistle",
              "icon": "https://gi.yatta.moe/assets/UI/UI_ItemIcon_112106.png",
              "rarity": 3,
              "qty": 6
            },
            {
              "id": 113060,
              "name": "Fading Candle",
              "icon": "https://gi.yatta.moe/assets/UI/UI_ItemIcon_113060.png",
              "rarity": 5,
              "qty": 1
            }
          ]
        },
        {
          "level": 9,
          "moraCost": 450000,
          "items": [
            {
              "id": 104355,
              "name": "Philosophies of Conflict",
              "icon": "https://gi.yatta.moe/assets/UI/UI_ItemIcon_104355.png",
              "rarity": 4,
              "qty": 12
            },
            {
              "id": 112106,
              "name": "Saurian-Crowned Warrior's Golden Whistle",
              "icon": "https://gi.yatta.moe/assets/UI/UI_ItemIcon_112106.png",
              "rarity": 3,
              "qty": 9
            },
            {
              "id": 113060,
              "name": "Fading Candle",
              "icon": "https://gi.yatta.moe/assets/UI/UI_ItemIcon_113060.png",
              "rarity": 5,
              "qty": 2
            }
          ]
        },
        {
          "level": 10,
          "moraCost": 700000,
          "items": [
            {
              "id": 104319,
              "name": "Crown of Insight",
              "icon": "https://gi.yatta.moe/assets/UI/UI_ItemIcon_104319.png",
              "rarity": 5,
              "qty": 1
            },
            {
              "id": 104355,
              "name": "Philosophies of Conflict",
              "icon": "https://gi.yatta.moe/assets/UI/UI_ItemIcon_104355.png",
              "rarity": 4,
              "qty": 16
            },
            {
              "id": 112106,
              "name": "Saurian-Crowned Warrior's Golden Whistle",
              "icon": "https://gi.yatta.moe/assets/UI/UI_ItemIcon_112106.png",
              "rarity": 3,
              "qty": 12
            },
            {
              "id": 113060,
              "name": "Fading Candle",
              "icon": "https://gi.yatta.moe/assets/UI/UI_ItemIcon_113060.png",
              "rarity": 5,
              "qty": 2
            }
          ]
        },
        {
          "level": 11,
          "moraCost": null,
          "items": []
        },
        {
          "level": 12,
          "moraCost": null,
          "items": []
        },
        {
          "level": 13,
          "moraCost": null,
          "items": []
        },
        {
          "level": 14,
          "moraCost": null,
          "items": []
        },
        {
          "level": 15,
          "moraCost": null,
          "items": []
        }
      ]
    }
  ],
  "passiveTalents": [
    {
      "name": "Mountain Echoes",
      "description": "After nearby party members trigger a Nightsoul Burst, Kachina's Geo DMG Bonus increases by 20% for 12s.",
      "icon": "https://gi.yatta.moe/assets/UI/UI_Talent_S_Kachina_05.png"
    },
    {
      "name": "The Weight of Stone",
      "description": "Turbo Twirly's DMG is increased by 20% of Kachina's DEF.",
      "icon": "https://gi.yatta.moe/assets/UI/UI_Talent_S_Kachina_06.png"
    },
    {
      "name": "Night Realm's Gift: Heart of Unity",
      "description": "After her Nightsoul points are depleted, Kachina will switch to consuming Phlogiston to maintain her Nightsoul's Blessing.\nWhile in an area with Phlogiston Mechanics within Natlan, she can use Nightsoul Transmission: Kachina. When the active character is currently sprinting, climbing, in a movement mode caused by certain Talents, or at a certain height in the air, the following will trigger when switching to Kachina: Kachina will enter the Nightsoul's Blessing state and ride Turbo Twirly when taking the field while gaining 30 Nightsoul points. Nightsoul Transmission can be triggered once every 10s by your own team.\n\nAdditionally, while in Natlan, Kachina will consume 90% less Stamina when climbing while riding Turbo Twirly.",
      "icon": "https://gi.yatta.moe/assets/UI/UI_Talent_S_Kachina_07.png"
    },
    {
      "name": "Boon of Crystal Flame",
      "description": "While in an area with Phlogiston Mechanics within Natlan, 20 Stamina will be restored when interacting with some harvestable items. Additionally, the location of nearby resources unique to Natlan will appear on your mini-map.",
      "icon": "https://gi.yatta.moe/assets/UI/UI_Talent_S_Kachina_08.png"
    }
  ],
  "constellations": [
    {
      "name": "Shards Are Gems Too",
      "description": "When Kachina mounts or dismounts Turbo Twirly, she will absorb nearby Elemental Shards created by Crystallize.\nAdditionally, when a party member picks up such a Shard, or triggers Lunar-Crystallize reactions, 3 Energy will be restored to Kachina. Energy can be restored this way once every 5s.",
      "icon": "https://gi.yatta.moe/assets/UI/UI_Talent_S_Kachina_01.png"
    },
    {
      "name": "Never Leave Home Without... Turbo Twirly",
      "description": "When Kachina uses \"Time to Get Serious!\", she will regain 20 Nightsoul points. If there is no Turbo Twirly belonging to her on the field, she will enter Nightsoul's Blessing and summon one.",
      "icon": "https://gi.yatta.moe/assets/UI/UI_Talent_S_Kachina_02.png"
    },
    {
      "name": "Improved Stabilizer",
      "description": "Increases the Level of Go, Go Turbo Twirly! by 3.\nMaximum upgrade level is 15.",
      "icon": "https://gi.yatta.moe/assets/UI/UI_Talent_U_Kachina_01.png"
    },
    {
      "name": "More Foes, More Caution",
      "description": "When there are 1/2/3/4 (or more) opponents within the Turbo Drill Field created by \"Time to Get Serious!\", the active character within the field gains 8%/12%/16%/20% increased DEF.",
      "icon": "https://gi.yatta.moe/assets/UI/UI_Talent_S_Kachina_03.png"
    },
    {
      "name": "All I've Collected Till Now",
      "description": "Increases the Level of Time to Get Serious! by 3.\nMaximum upgrade level is 15.",
      "icon": "https://gi.yatta.moe/assets/UI/UI_Talent_U_Kachina_02.png"
    },
    {
      "name": "This Time, I've Gotta Win",
      "description": "When your active character's Shield is replaced or destroyed for any reason, Kachina will deal 200% of her DEF as AoE Geo DMG. This effect can be triggered once every 5s.",
      "icon": "https://gi.yatta.moe/assets/UI/UI_Talent_S_Kachina_04.png"
    }
  ],
  "ascensionMaterials": [
    {
      "id": 101249,
      "name": "Quenepa Berry",
      "icon": "https://gi.yatta.moe/assets/UI/UI_ItemIcon_101249.png",
      "rarity": 1
    },
    {
      "id": 104171,
      "name": "Prithiva Topaz Sliver",
      "icon": "https://gi.yatta.moe/assets/UI/UI_ItemIcon_104171.png",
      "rarity": 2
    },
    {
      "id": 104172,
      "name": "Prithiva Topaz Fragment",
      "icon": "https://gi.yatta.moe/assets/UI/UI_ItemIcon_104172.png",
      "rarity": 3
    },
    {
      "id": 104173,
      "name": "Prithiva Topaz Chunk",
      "icon": "https://gi.yatta.moe/assets/UI/UI_ItemIcon_104173.png",
      "rarity": 4
    },
    {
      "id": 104174,
      "name": "Prithiva Topaz Gemstone",
      "icon": "https://gi.yatta.moe/assets/UI/UI_ItemIcon_104174.png",
      "rarity": 5
    },
    {
      "id": 104319,
      "name": "Crown of Insight",
      "icon": "https://gi.yatta.moe/assets/UI/UI_ItemIcon_104319.png",
      "rarity": 5
    },
    {
      "id": 104353,
      "name": "Teachings of Conflict",
      "icon": "https://gi.yatta.moe/assets/UI/UI_ItemIcon_104353.png",
      "rarity": 2
    },
    {
      "id": 104354,
      "name": "Guide to Conflict",
      "icon": "https://gi.yatta.moe/assets/UI/UI_ItemIcon_104354.png",
      "rarity": 3
    },
    {
      "id": 104355,
      "name": "Philosophies of Conflict",
      "icon": "https://gi.yatta.moe/assets/UI/UI_ItemIcon_104355.png",
      "rarity": 4
    },
    {
      "id": 112104,
      "name": "Sentry's Wooden Whistle",
      "icon": "https://gi.yatta.moe/assets/UI/UI_ItemIcon_112104.png",
      "rarity": 1
    },
    {
      "id": 112105,
      "name": "Warrior's Metal Whistle",
      "icon": "https://gi.yatta.moe/assets/UI/UI_ItemIcon_112105.png",
      "rarity": 2
    },
    {
      "id": 112106,
      "name": "Saurian-Crowned Warrior's Golden Whistle",
      "icon": "https://gi.yatta.moe/assets/UI/UI_ItemIcon_112106.png",
      "rarity": 3
    },
    {
      "id": 113060,
      "name": "Fading Candle",
      "icon": "https://gi.yatta.moe/assets/UI/UI_ItemIcon_113060.png",
      "rarity": 5
    },
    {
      "id": 113065,
      "name": "Overripe Flamegranate",
      "icon": "https://gi.yatta.moe/assets/UI/UI_ItemIcon_113065.png",
      "rarity": 4
    }
  ],
  "ascensionGems": [
    {
      "id": 104171,
      "name": "Prithiva Topaz Sliver",
      "icon": "https://gi.yatta.moe/assets/UI/UI_ItemIcon_104171.png",
      "rarity": 2
    },
    {
      "id": 104172,
      "name": "Prithiva Topaz Fragment",
      "icon": "https://gi.yatta.moe/assets/UI/UI_ItemIcon_104172.png",
      "rarity": 3
    },
    {
      "id": 104173,
      "name": "Prithiva Topaz Chunk",
      "icon": "https://gi.yatta.moe/assets/UI/UI_ItemIcon_104173.png",
      "rarity": 4
    },
    {
      "id": 104174,
      "name": "Prithiva Topaz Gemstone",
      "icon": "https://gi.yatta.moe/assets/UI/UI_ItemIcon_104174.png",
      "rarity": 5
    }
  ],
  "localSpecialty": [
    {
      "id": 101249,
      "name": "Quenepa Berry",
      "icon": "https://gi.yatta.moe/assets/UI/UI_ItemIcon_101249.png",
      "rarity": 1
    }
  ],
  "talentBooks": [
    {
      "id": 104319,
      "name": "Crown of Insight",
      "icon": "https://gi.yatta.moe/assets/UI/UI_ItemIcon_104319.png",
      "rarity": 5
    },
    {
      "id": 104353,
      "name": "Teachings of Conflict",
      "icon": "https://gi.yatta.moe/assets/UI/UI_ItemIcon_104353.png",
      "rarity": 2
    },
    {
      "id": 104354,
      "name": "Guide to Conflict",
      "icon": "https://gi.yatta.moe/assets/UI/UI_ItemIcon_104354.png",
      "rarity": 3
    },
    {
      "id": 104355,
      "name": "Philosophies of Conflict",
      "icon": "https://gi.yatta.moe/assets/UI/UI_ItemIcon_104355.png",
      "rarity": 4
    }
  ],
  "enemyDrops": [
    {
      "id": 112104,
      "name": "Sentry's Wooden Whistle",
      "icon": "https://gi.yatta.moe/assets/UI/UI_ItemIcon_112104.png",
      "rarity": 1
    },
    {
      "id": 112105,
      "name": "Warrior's Metal Whistle",
      "icon": "https://gi.yatta.moe/assets/UI/UI_ItemIcon_112105.png",
      "rarity": 2
    },
    {
      "id": 112106,
      "name": "Saurian-Crowned Warrior's Golden Whistle",
      "icon": "https://gi.yatta.moe/assets/UI/UI_ItemIcon_112106.png",
      "rarity": 3
    },
    {
      "id": 113060,
      "name": "Fading Candle",
      "icon": "https://gi.yatta.moe/assets/UI/UI_ItemIcon_113060.png",
      "rarity": 5
    },
    {
      "id": 113065,
      "name": "Overripe Flamegranate",
      "icon": "https://gi.yatta.moe/assets/UI/UI_ItemIcon_113065.png",
      "rarity": 4
    }
  ],
  "promotes": [
    {
      "promoteLevel": 0,
      "unlockMaxLevel": 20,
      "moraCost": null,
      "requiredPlayerLevel": null,
      "items": []
    },
    {
      "promoteLevel": 1,
      "unlockMaxLevel": 40,
      "moraCost": 20000,
      "requiredPlayerLevel": 15,
      "items": [
        {
          "id": 101249,
          "name": "Quenepa Berry",
          "icon": "https://gi.yatta.moe/assets/UI/UI_ItemIcon_101249.png",
          "rarity": 1,
          "qty": 3
        },
        {
          "id": 104171,
          "name": "Prithiva Topaz Sliver",
          "icon": "https://gi.yatta.moe/assets/UI/UI_ItemIcon_104171.png",
          "rarity": 2,
          "qty": 1
        },
        {
          "id": 112104,
          "name": "Sentry's Wooden Whistle",
          "icon": "https://gi.yatta.moe/assets/UI/UI_ItemIcon_112104.png",
          "rarity": 1,
          "qty": 3
        }
      ]
    },
    {
      "promoteLevel": 2,
      "unlockMaxLevel": 50,
      "moraCost": 40000,
      "requiredPlayerLevel": 25,
      "items": [
        {
          "id": 101249,
          "name": "Quenepa Berry",
          "icon": "https://gi.yatta.moe/assets/UI/UI_ItemIcon_101249.png",
          "rarity": 1,
          "qty": 10
        },
        {
          "id": 104172,
          "name": "Prithiva Topaz Fragment",
          "icon": "https://gi.yatta.moe/assets/UI/UI_ItemIcon_104172.png",
          "rarity": 3,
          "qty": 3
        },
        {
          "id": 112104,
          "name": "Sentry's Wooden Whistle",
          "icon": "https://gi.yatta.moe/assets/UI/UI_ItemIcon_112104.png",
          "rarity": 1,
          "qty": 15
        },
        {
          "id": 113065,
          "name": "Overripe Flamegranate",
          "icon": "https://gi.yatta.moe/assets/UI/UI_ItemIcon_113065.png",
          "rarity": 4,
          "qty": 2
        }
      ]
    },
    {
      "promoteLevel": 3,
      "unlockMaxLevel": 60,
      "moraCost": 60000,
      "requiredPlayerLevel": 30,
      "items": [
        {
          "id": 101249,
          "name": "Quenepa Berry",
          "icon": "https://gi.yatta.moe/assets/UI/UI_ItemIcon_101249.png",
          "rarity": 1,
          "qty": 20
        },
        {
          "id": 104172,
          "name": "Prithiva Topaz Fragment",
          "icon": "https://gi.yatta.moe/assets/UI/UI_ItemIcon_104172.png",
          "rarity": 3,
          "qty": 6
        },
        {
          "id": 112105,
          "name": "Warrior's Metal Whistle",
          "icon": "https://gi.yatta.moe/assets/UI/UI_ItemIcon_112105.png",
          "rarity": 2,
          "qty": 12
        },
        {
          "id": 113065,
          "name": "Overripe Flamegranate",
          "icon": "https://gi.yatta.moe/assets/UI/UI_ItemIcon_113065.png",
          "rarity": 4,
          "qty": 4
        }
      ]
    },
    {
      "promoteLevel": 4,
      "unlockMaxLevel": 70,
      "moraCost": 80000,
      "requiredPlayerLevel": 35,
      "items": [
        {
          "id": 101249,
          "name": "Quenepa Berry",
          "icon": "https://gi.yatta.moe/assets/UI/UI_ItemIcon_101249.png",
          "rarity": 1,
          "qty": 30
        },
        {
          "id": 104173,
          "name": "Prithiva Topaz Chunk",
          "icon": "https://gi.yatta.moe/assets/UI/UI_ItemIcon_104173.png",
          "rarity": 4,
          "qty": 3
        },
        {
          "id": 112105,
          "name": "Warrior's Metal Whistle",
          "icon": "https://gi.yatta.moe/assets/UI/UI_ItemIcon_112105.png",
          "rarity": 2,
          "qty": 18
        },
        {
          "id": 113065,
          "name": "Overripe Flamegranate",
          "icon": "https://gi.yatta.moe/assets/UI/UI_ItemIcon_113065.png",
          "rarity": 4,
          "qty": 8
        }
      ]
    },
    {
      "promoteLevel": 5,
      "unlockMaxLevel": 80,
      "moraCost": 100000,
      "requiredPlayerLevel": 40,
      "items": [
        {
          "id": 101249,
          "name": "Quenepa Berry",
          "icon": "https://gi.yatta.moe/assets/UI/UI_ItemIcon_101249.png",
          "rarity": 1,
          "qty": 45
        },
        {
          "id": 104173,
          "name": "Prithiva Topaz Chunk",
          "icon": "https://gi.yatta.moe/assets/UI/UI_ItemIcon_104173.png",
          "rarity": 4,
          "qty": 6
        },
        {
          "id": 112106,
          "name": "Saurian-Crowned Warrior's Golden Whistle",
          "icon": "https://gi.yatta.moe/assets/UI/UI_ItemIcon_112106.png",
          "rarity": 3,
          "qty": 12
        },
        {
          "id": 113065,
          "name": "Overripe Flamegranate",
          "icon": "https://gi.yatta.moe/assets/UI/UI_ItemIcon_113065.png",
          "rarity": 4,
          "qty": 12
        }
      ]
    },
    {
      "promoteLevel": 6,
      "unlockMaxLevel": 90,
      "moraCost": 120000,
      "requiredPlayerLevel": 50,
      "items": [
        {
          "id": 101249,
          "name": "Quenepa Berry",
          "icon": "https://gi.yatta.moe/assets/UI/UI_ItemIcon_101249.png",
          "rarity": 1,
          "qty": 60
        },
        {
          "id": 104174,
          "name": "Prithiva Topaz Gemstone",
          "icon": "https://gi.yatta.moe/assets/UI/UI_ItemIcon_104174.png",
          "rarity": 5,
          "qty": 6
        },
        {
          "id": 112106,
          "name": "Saurian-Crowned Warrior's Golden Whistle",
          "icon": "https://gi.yatta.moe/assets/UI/UI_ItemIcon_112106.png",
          "rarity": 3,
          "qty": 24
        },
        {
          "id": 113065,
          "name": "Overripe Flamegranate",
          "icon": "https://gi.yatta.moe/assets/UI/UI_ItemIcon_113065.png",
          "rarity": 4,
          "qty": 20
        }
      ]
    }
  ]
}